Metadata-Version: 1.0
Name: zqadd
Version: 0.1
Summary: setup example
Home-page: https://github.com/zqGitHubs/zqceshiadd
Author: zq
Author-email: 1063011191@qq.com
License: MIT
Platform: any
